MANIFEST.in
README.txt
run.py
setup.py
webstag/__init__.py
webstag/photo.py
webstag/video.py
webstag.egg-info/PKG-INFO
webstag.egg-info/SOURCES.txt
webstag.egg-info/dependency_links.txt
webstag.egg-info/entry_points.txt
webstag.egg-info/not-zip-safe
webstag.egg-info/requires.txt
webstag.egg-info/top_level.txt
webstag/resources/css/main.css
webstag/resources/images/glyphicons-halflings-white.png
webstag/resources/images/glyphicons-halflings.png
webstag/resources/images/video-bottom.gif
webstag/resources/images/video-top.gif
webstag/resources/js/main.js
webstag/resources/js/plugins.js
webstag/resources/vendor/jquery-1.8.3.min.js
webstag/resources/vendor/modernizr-2.6.2-respond-1.1.0.min.js
webstag/resources/vendor/bootstrap/bootstrap-responsive.css
webstag/resources/vendor/bootstrap/bootstrap-responsive.min.css
webstag/resources/vendor/bootstrap/bootstrap.css
webstag/resources/vendor/bootstrap/bootstrap.js
webstag/resources/vendor/bootstrap/bootstrap.min.css
webstag/resources/vendor/bootstrap/bootstrap.min.js
webstag/resources/vendor/colorbox/colorbox.css
webstag/resources/vendor/colorbox/jquery.colorbox-min.js
webstag/resources/vendor/colorbox/jquery.colorbox.js
webstag/resources/vendor/colorbox/i18n/jquery.colorbox-ar.js
webstag/resources/vendor/colorbox/i18n/jquery.colorbox-cs.js
webstag/resources/vendor/colorbox/i18n/jquery.colorbox-da.js
webstag/resources/vendor/colorbox/i18n/jquery.colorbox-de.js
webstag/resources/vendor/colorbox/i18n/jquery.colorbox-es.js
webstag/resources/vendor/colorbox/i18n/jquery.colorbox-fa.js
webstag/resources/vendor/colorbox/i18n/jquery.colorbox-fr.js
webstag/resources/vendor/colorbox/i18n/jquery.colorbox-hr.js
webstag/resources/vendor/colorbox/i18n/jquery.colorbox-hu.js
webstag/resources/vendor/colorbox/i18n/jquery.colorbox-it.js
webstag/resources/vendor/colorbox/i18n/jquery.colorbox-ja.js
webstag/resources/vendor/colorbox/i18n/jquery.colorbox-kr.js
webstag/resources/vendor/colorbox/i18n/jquery.colorbox-lv.js
webstag/resources/vendor/colorbox/i18n/jquery.colorbox-nl.js
webstag/resources/vendor/colorbox/i18n/jquery.colorbox-no.js
webstag/resources/vendor/colorbox/i18n/jquery.colorbox-pl.js
