Metadata-Version: 1.1
Name: webstag
Version: 0.3
Summary: Generate static HTML galleries with photos and videos
Home-page: https://gitorious.org/webstag
Author: Aurelien Bompard
Author-email: aurelien@bompard.org
License: GPLv3+
Platform: UNKNOWN
Classifier: Development Status :: 5 - Production/Stable
Classifier: Environment :: Console
Classifier: Environment :: Web Environment
Classifier: Intended Audience :: End Users/Desktop
Classifier: License :: OSI Approved :: GNU General Public License v3 or later (GPLv3+)
Classifier: Topic :: Multimedia :: Graphics :: Viewers
Classifier: Topic :: Multimedia :: Video
